{
    "1": [
        [
            [
                1,
                26.34224140820325,
                6.519491535375096,
                21.053597692528296,
                -105.85879128100316,
                30.352771166423537,
                52.81863164659808,
                29.21677219913387,
                -98.26605823258234,
                39.3216203248619,
                65.2470322406893,
                26.0125454069957,
                -42.74621721551449,
                36.79188452857677
            ],
            null
        ]
    ],
    "2": [
        [
            [
                2,
                22.2567846325078,
                107.68128840188348,
                22.652602019288423,
                -16.776079125741603,
                36.97083955916596,
                null,
                null,
                null,
                null,
                41.534264662062924,
                29.302049535355117,
                -27.92799211782858,
                34.500431670790064
            ],
            [
                2,
                22.821335024609155,
                108.00965541735263,
                23.65260201928842,
                -10.188593340333682,
                34.97083955916597,
                null,
                null,
                null,
                null,
                44.90735543556548,
                29.322049535355116,
                -22.007710276608634,
                34.54043167079007
            ]
        ]
    ],
    "3": [],
    "4": [],
    "5": [],
    "6": [],
    "7": [],
    "8": [],
    "9": [],
    "10": []
}