{
    "1": [
        [
            [
                0,
                22.328934589482564,
                110.20497662587053,
                35.390802156929595,
                -8.279316266727209,
                31.383533142944565,
                6.5420270177233135,
                25.08824734920562,
                -91.39545300472133,
                35.14122190670427,
                null,
                null,
                null,
                null
            ],
            null
        ],
        [
            [
                0,
                22.57538913773204,
                114.93048244204556,
                35.85679735342312,
                -7.007154497593206,
                28.461851279078225,
                10.108272536038044,
                25.68899716787341,
                -83.20263622616665,
                35.406872807828535,
                null,
                null,
                null,
                null
            ],
            null
        ],
        [
            [
                1,
                31.258683921401715,
                8.36696198135877,
                23.242915565477823,
                null,
                null,
                99.69962464717224,
                34.99997628700886,
                -9.600584143837466,
                27.611554813443053,
                4.236541302823639,
                24.956169335714677,
                -113.83299072350337,
                25.981814651496705
            ],
            null
        ],
        [
            [
                1,
                28.5402339713386,
                6.096851152709405,
                24.18991374460336,
                null,
                null,
                103.51264865594408,
                36.80696095760419,
                -13.841744922441706,
                28.29520627441645,
                6.176710179918587,
                25.24056106919113,
                -115.87898426499856,
                25.331033680739694
            ],
            null
        ]
    ],
    "2": [],
    "3": [
        [
            [
                2,
                36.98113225142966,
                13.905136265889439,
                27.505817935102296,
                -47.08867713938838,
                29.837837698861538,
                null,
                null,
                null,
                null,
                7.692201490606351,
                32.982398450306775,
                -34.44704076252452,
                35.55018234572205
            ],
            [
                2,
                34.98113225142967,
                9.647479107725701,
                27.2858179351023,
                -49.80632441567252,
                30.577837698861536,
                null,
                null,
                null,
                null,
                6.592834590044845,
                33.98239845030679,
                -34.61251571537849,
                35.43018234572206
            ]
        ]
    ],
    "4": [
        [
            [
                2,
                38.981132251429656,
                19.03879342405315,
                27.31886541863989,
                -42.98102986310437,
                29.17741630473784,
                null,
                null,
                null,
                null,
                10.291568391167885,
                32.04815957831693,
                -33.36356580967086,
                36.1711054798311
            ],
            [
                2,
                36.98113225142966,
                13.905136265889439,
                27.505817935102296,
                -47.08867713938838,
                29.837837698861538,
                null,
                null,
                null,
                null,
                7.692201490606351,
                32.982398450306775,
                -34.44704076252452,
                35.55018234572205
            ]
        ]
    ],
    "5": [],
    "6": [],
    "7": [],
    "8": [],
    "9": [],
    "10": []
}