{
    "1": [
        [
            [
                0,
                23.78753639875837,
                21.47755150122191,
                23.23058652360078,
                -7.0636047219488205,
                28.224054601793263,
                96.6017509330398,
                21.98105400534364,
                -105.55044248308593,
                36.147885594384555,
                null,
                null,
                null,
                null
            ],
            null
        ],
        [
            [
                2,
                31.43304848662519,
                6.174886712840362,
                27.209183452098664,
                -40.4237361921966,
                28.166124484316946,
                null,
                null,
                null,
                null,
                91.39368479204882,
                29.707395662934406,
                -9.980326057345337,
                34.30598703030677
            ],
            null
        ]
    ],
    "2": [
        [
            [
                0,
                25.787536398758363,
                22.35602643880065,
                22.249118934969527,
                -9.281863823466296,
                30.72405460179326,
                98.10499212974712,
                21.00180089810231,
                -111.33861708089903,
                36.17514947080828,
                null,
                null,
                null,
                null
            ],
            [
                0,
                23.78753639875837,
                21.47755150122191,
                23.23058652360078,
                -7.0636047219488205,
                28.224054601793263,
                96.6017509330398,
                21.98105400534364,
                -105.55044248308593,
                36.147885594384555,
                null,
                null,
                null,
                null
            ]
        ],
        [
            [
                2,
                37.47021832276361,
                14.025934989205021,
                25.69639095818269,
                -34.96891351493775,
                26.338162996611096,
                null,
                null,
                null,
                null,
                99.32663872652475,
                26.16428046647097,
                -9.195176996848616,
                34.01562028632476
            ],
            [
                2,
                35.470218322763614,
                8.84750591317112,
                25.949360170695794,
                -39.70541254239947,
                27.073220267840227,
                null,
                null,
                null,
                null,
                94.55938958699551,
                27.135720043705348,
                -10.331759167856035,
                33.96105398074883
            ]
        ],
        [
            [
                1,
                34.59507858610494,
                15.009146044164822,
                22.217146877875457,
                -22.281697424118647,
                34.40571653856672,
                44.38262847700099,
                36.88414518297593,
                -47.54622251214147,
                25.846447792083314,
                29.612004897833913,
                22.62688991554306,
                -33.90443799207213,
                22.621677870297074
            ],
            [
                1,
                32.59507858610495,
                9.410180190050028,
                22.077146877875457,
                -21.918378447887733,
                33.80571653856672,
                46.13516177543664,
                36.86414518297592,
                -51.09253790915221,
                26.56644779208331,
                24.29591056255299,
                22.926889915543057,
                -39.295138349976014,
                22.56167787029707
            ]
        ]
    ],
    "3": [
        [
            [
                1,
                36.59507858610493,
                21.610111898279545,
                22.002444245977276,
                -21.81301640034951,
                34.897752429858144,
                43.64009517856564,
                36.9173034879193,
                -42.6219071151306,
                25.046910948999553,
                35.986099233114956,
                22.459331034801522,
                -27.535737634168115,
                22.551601556578316
            ],
            [
                1,
                34.59507858610494,
                15.009146044164822,
                22.217146877875457,
                -22.281697424118647,
                34.40571653856672,
                44.38262847700099,
                36.88414518297593,
                -47.54622251214147,
                25.846447792083314,
                29.612004897833913,
                22.62688991554306,
                -33.90443799207213,
                22.621677870297074
            ]
        ]
    ],
    "4": [],
    "5": [],
    "6": [],
    "7": [],
    "8": [],
    "9": [],
    "10": []
}