{
    "1": [
        [
            [
                2,
                28.907486843928154,
                9.477182567029807,
                25.942513492844412,
                -7.525761382326967,
                34.93654561030561,
                null,
                null,
                null,
                null,
                78.48834502674707,
                32.506566772069526,
                -74.29115238518857,
                27.20542431347784
            ],
            null
        ],
        [
            [
                2,
                31.891695392406127,
                6.288215465516032,
                27.441661753161068,
                -61.89290942662274,
                28.897086336560296,
                null,
                null,
                null,
                null,
                109.23331371967907,
                37.366991786442924,
                -39.10228568635239,
                20.953484088100318
            ],
            null
        ],
        [
            [
                2,
                27.687984906263786,
                5.590484822481756,
                25.29245505969464,
                null,
                null,
                null,
                null,
                null,
                null,
                31.57845306976475,
                37.223919185046256,
                -19.794106746722264,
                37.9071464056569
            ],
            null
        ],
        [
            [
                2,
                33.54880348434757,
                7.680114042051785,
                26.79636814947007,
                -45.97566327714632,
                38.06373973277057,
                null,
                null,
                null,
                null,
                101.85115082752719,
                30.78932008662735,
                -13.683894220621472,
                28.654832650569382
            ],
            null
        ],
        [
            [
                2,
                29.922892219386362,
                5.061771626841562,
                27.396173797488395,
                -42.14003094874954,
                36.11582987305639,
                null,
                null,
                null,
                null,
                99.74346492363583,
                32.2503747147762,
                -17.43644033763627,
                30.76633792408929
            ],
            null
        ]
    ],
    "2": [
        [
            [
                0,
                22.598362917228464,
                20.403992899189063,
                24.207662155590615,
                -13.337156340206207,
                33.24629007594328,
                60.140687991264144,
                29.953970795727983,
                -100.11956908036848,
                37.70683476589285,
                null,
                null,
                null,
                null
            ],
            [
                0,
                22.05848700139503,
                21.744034360889998,
                25.20766215559061,
                -8.377800918328944,
                31.246290075943286,
                64.07988377303388,
                30.053970795727984,
                -92.32994131351649,
                37.686834765892854,
                null,
                null,
                null,
                null
            ]
        ]
    ],
    "3": [
        [
            [
                0,
                24.36031537452898,
                20.121950570417027,
                23.20766215559062,
                -18.738512629154513,
                35.24629007594327,
                56.78549134242337,
                29.613970795727983,
                -107.34719771429155,
                37.70683476589286,
                null,
                null,
                null,
                null
            ],
            [
                0,
                22.598362917228464,
                20.403992899189063,
                24.207662155590615,
                -13.337156340206207,
                33.24629007594328,
                60.140687991264144,
                29.953970795727983,
                -100.11956908036848,
                37.70683476589285,
                null,
                null,
                null,
                null
            ]
        ]
    ],
    "4": [
        [
            [
                0,
                26.360315374528973,
                21.298277179886224,
                22.23589491293809,
                -24.181499979861627,
                37.746290075943264,
                54.75866363182382,
                28.6604193835948,
                -113.64845740997346,
                37.8231932441135,
                null,
                null,
                null,
                null
            ],
            [
                0,
                24.36031537452898,
                20.121950570417027,
                23.20766215559062,
                -18.738512629154513,
                35.24629007594327,
                56.78549134242337,
                29.613970795727983,
                -107.34719771429155,
                37.70683476589286,
                null,
                null,
                null,
                null
            ]
        ]
    ],
    "5": [],
    "6": [],
    "7": [],
    "8": [],
    "9": [],
    "10": []
}