{
    "1": [
        [
            [
                1,
                23.255230889442117,
                116.9047190192428,
                31.249557296217844,
                -6.200350501890284,
                27.84922807623171,
                112.89244353460577,
                34.77604072339152,
                -7.664258996107151,
                29.91616237330607,
                49.955040327422125,
                26.413428959951627,
                -58.66321796796444,
                25.43521349937874
            ],
            null
        ],
        [
            [
                2,
                37.50948063947415,
                9.15792971352535,
                26.998456813565546,
                -97.49104953055847,
                21.512693088321328,
                null,
                null,
                null,
                null,
                109.53204899076671,
                35.66235389821798,
                -8.011949896070082,
                34.857031915217135
            ],
            null
        ],
        [
            [
                2,
                32.54943137793971,
                5.7326040177993605,
                27.522686140945602,
                -110.018918492632,
                23.29148404400974,
                null,
                null,
                null,
                null,
                110.96186552353731,
                36.793690699343585,
                -6.698650434472313,
                37.416907958882504
            ],
            null
        ]
    ],
    "2": [],
    "3": [],
    "4": [],
    "5": [],
    "6": [],
    "7": [],
    "8": [],
    "9": [],
    "10": []
}