{
    "1": [
        [
            [
                2,
                29.40726273732148,
                12.090209151586464,
                24.160482826628247,
                -5.731058975221629,
                34.20803396573524,
                null,
                null,
                null,
                null,
                77.03083825626157,
                27.867717281915453,
                -103.84150920960968,
                25.472039853443395
            ],
            null
        ],
        [
            [
                2,
                27.77956936809899,
                7.675957015194911,
                24.66259903523747,
                -5.916820455666482,
                31.2407380893806,
                null,
                null,
                null,
                null,
                79.00779392877143,
                28.388860447974615,
                -102.68742517657859,
                26.00727711291094
            ],
            null
        ],
        [
            [
                2,
                27.699447384499095,
                5.649880672213897,
                24.299252892744175,
                -57.23313069483004,
                35.87849974931072,
                null,
                null,
                null,
                null,
                33.44547575595419,
                28.954884666809306,
                null,
                null
            ],
            null
        ],
        [
            [
                1,
                31.927022835467177,
                25.96493129375841,
                31.541921112696855,
                -5.852234559741646,
                34.0747752090615,
                46.848571080906595,
                38.554171066810824,
                -51.982239442061314,
                24.636534359410852,
                88.22712152315188,
                25.78463855353518,
                -47.88943651280829,
                21.545367535998935
            ],
            null
        ]
    ],
    "2": [],
    "3": [],
    "4": [],
    "5": [],
    "6": [],
    "7": [],
    "8": [],
    "9": [],
    "10": []
}