{
    "1": [
        [
            [
                0,
                31.09807010853677,
                10.802158947939471,
                25.65265251405247,
                -6.026225732439755,
                34.012021942955016,
                94.6468061784624,
                34.71137828977028,
                -113.77430175200588,
                29.579362827812396,
                null,
                null,
                null,
                null
            ],
            null
        ],
        [
            [
                2,
                22.571610866149634,
                25.391684294083916,
                25.49975488558664,
                -10.047554290971505,
                35.24598165740139,
                null,
                null,
                null,
                null,
                95.09909945123405,
                23.651457598001524,
                -68.92733026660443,
                39.400244778464156
            ],
            null
        ],
        [
            [
                2,
                23.161420492940948,
                30.635764536185786,
                25.65579195599516,
                -8.703827201609688,
                32.498985634288466,
                null,
                null,
                null,
                null,
                95.66004986103376,
                23.865304455792966,
                -64.87804972252324,
                39.615652250360206
            ],
            null
        ],
        [
            [
                2,
                23.655135096617908,
                34.29119316069654,
                24.877596071265174,
                -5.741357649493409,
                26.918042302609656,
                null,
                null,
                null,
                null,
                98.82414144890237,
                26.310389961590698,
                -50.52405612353499,
                39.83658789183392
            ],
            null
        ],
        [
            [
                0,
                20.26629782728218,
                18.901239014141083,
                22.272676003564523,
                -5.874342893142398,
                23.88171097577746,
                117.9721883943879,
                22.67680057554703,
                -39.446678589017154,
                34.37381521847615,
                null,
                null,
                null,
                null
            ],
            null
        ]
    ],
    "2": [],
    "3": [
        [
            [
                2,
                24.220669289056318,
                23.66393708902752,
                23.525081209597715,
                -24.22152826784273,
                39.74598165740137,
                null,
                null,
                null,
                null,
                95.2196495337627,
                21.671355412662585,
                -85.48756736453832,
                39.58437289398001
            ],
            [
                2,
                22.656669387088762,
                24.109583324487403,
                24.499754885586643,
                -16.802768646475386,
                37.24598165740138,
                null,
                null,
                null,
                null,
                94.74114712543007,
                22.651457598001528,
                -77.36367618263978,
                39.42024477846415
            ]
        ]
    ],
    "4": [],
    "5": [],
    "6": [],
    "7": [],
    "8": [],
    "9": [],
    "10": []
}