{
    "1": [
        [
            [
                1,
                39.386287871091135,
                13.623417020249118,
                20.67090827118443,
                -58.51386773863253,
                32.93113313147278,
                33.503967823388216,
                32.72642029084868,
                -101.80810229998258,
                38.55885152053048,
                20.36972285838114,
                36.42165055162669,
                -84.58875838520117,
                34.79961118973838
            ],
            null
        ],
        [
            [
                2,
                38.1263973473227,
                12.417703080230043,
                20.93459690471047,
                -49.21978927159443,
                37.37872278096569,
                null,
                null,
                null,
                null,
                16.021419680093526,
                31.401049810992685,
                -17.56722448582885,
                36.21209247179179
            ],
            null
        ],
        [
            [
                2,
                38.777884133291366,
                12.75160446850543,
                20.258592063723366,
                -59.985912078841395,
                38.09041773539931,
                null,
                null,
                null,
                null,
                35.96166306271646,
                31.296101850843478,
                -16.503480637770448,
                33.95030625306487
            ],
            null
        ]
    ],
    "2": [],
    "3": [],
    "4": [],
    "5": [],
    "6": [],
    "7": [],
    "8": [],
    "9": [],
    "10": []
}