{
    "1": [
        [
            [
                1,
                37.029031970113216,
                7.9308429632975335,
                29.204439384811472,
                -85.67892090082736,
                37.37973179553902,
                94.94795933804632,
                24.567596409645994,
                -56.58259692836561,
                24.79921765103631,
                72.21877298476802,
                29.322179004809385,
                -31.67595812980385,
                35.96990213570768
            ],
            null
        ],
        [
            [
                1,
                31.44486927382232,
                6.956063367977777,
                23.496781901077824,
                null,
                null,
                60.179010737356634,
                29.595967920450583,
                -97.82897723386247,
                31.671970927645877,
                113.28280248565227,
                37.32781280921347,
                null,
                null
            ],
            null
        ]
    ],
    "2": [],
    "3": [],
    "4": [],
    "5": [],
    "6": [
        [
            [
                0,
                37.0448692738223,
                107.57744364717405,
                37.24781280921344,
                -54.99984875187431,
                24.181268980513206,
                36.43628179983881,
                23.23678190107782,
                null,
                null,
                null,
                null,
                null,
                null
            ],
            [
                1,
                37.0448692738223,
                29.53823811346666,
                23.23678190107782,
                null,
                null,
                70.32681344409997,
                29.455967920450576,
                -91.60918054150966,
                31.331970927645884,
                107.78091541486964,
                37.46781280921344,
                -61.1796488985288,
                25.021268980513206
            ]
        ]
    ],
    "7": [],
    "8": [],
    "9": [],
    "10": []
}