{
    "1": [
        [
            [
                2,
                30.303691814809834,
                47.46996814748267,
                32.09974165306583,
                -7.986124760538075,
                38.735167627184836,
                null,
                null,
                null,
                null,
                65.76888559992987,
                24.00600425361926,
                -70.46097549319227,
                28.681719513397628
            ],
            null
        ],
        [
            [
                0,
                27.555068043062402,
                109.00822242434981,
                23.027102327720762,
                -7.338052008009527,
                33.68157525413059,
                50.49362588785169,
                31.46064081846189,
                -58.06262299276898,
                28.413574770935586,
                null,
                null,
                null,
                null
            ],
            null
        ],
        [
            [
                2,
                30.054384822324188,
                8.219544089020268,
                20.89799822591413,
                -96.85809017104374,
                35.17704437305325,
                null,
                null,
                null,
                null,
                25.002676102530284,
                33.20218397368808,
                -111.96485494133405,
                23.37031008763093
            ],
            null
        ]
    ],
    "2": [
        [
            [
                0,
                27.481503804599313,
                111.26680554633953,
                23.027102327720762,
                -10.81470534922471,
                35.681575254130586,
                48.72743976447083,
                30.460640818461894,
                -58.4612760923867,
                28.27357477093559,
                null,
                null,
                null,
                null
            ],
            [
                0,
                27.555068043062402,
                109.00822242434981,
                23.027102327720762,
                -7.338052008009527,
                33.68157525413059,
                50.49362588785169,
                31.46064081846189,
                -58.06262299276898,
                28.413574770935586,
                null,
                null,
                null,
                null
            ]
        ],
        [
            [
                2,
                34.81146653605214,
                14.935543197443852,
                20.75557102341195,
                -95.96246859089776,
                36.04285028499484,
                null,
                null,
                null,
                null,
                25.139558033092868,
                30.582934498131884,
                -98.32932390866651,
                22.368773030594472
            ],
            [
                2,
                32.811466536052144,
                8.798941713069269,
                21.73826356730302,
                -94.7333819884775,
                36.02963974089276,
                null,
                null,
                null,
                null,
                23.88581336263377,
                31.50397719513402,
                -103.89368457912627,
                22.374745195132803
            ]
        ]
    ],
    "3": [],
    "4": [],
    "5": [],
    "6": [],
    "7": [],
    "8": [],
    "9": [],
    "10": []
}