{
    "1": [
        [
            [
                2,
                32.74180026756653,
                8.796802359795748,
                21.047903539600284,
                -15.370694011637113,
                33.66895344648507,
                null,
                null,
                null,
                null,
                89.26584860623815,
                22.828744236718403,
                -114.01360905544452,
                29.202080636192864
            ],
            null
        ],
        [
            [
                1,
                36.01205344087205,
                null,
                null,
                -64.6654257781837,
                36.008425767047584,
                100.87702019519753,
                29.20354217726302,
                -62.979987768133185,
                21.317023939466274,
                8.468106964752565,
                24.40913093158791,
                -91.56284866342514,
                32.74021713594161
            ],
            null
        ]
    ],
    "2": [
        [
            [
                1,
                36.16120711794265,
                null,
                null,
                -64.61570974550813,
                35.97761551674286,
                104.47318069826076,
                28.310052777030883,
                -55.44636988779257,
                20.67733545438336,
                14.298798654479754,
                24.44913093158791,
                -89.91319214177184,
                32.84984523986236
            ],
            [
                1,
                36.01205344087205,
                null,
                null,
                -64.6654257781837,
                36.008425767047584,
                100.87702019519753,
                29.20354217726302,
                -62.979987768133185,
                21.317023939466274,
                8.468106964752565,
                24.40913093158791,
                -91.56284866342514,
                32.74021713594161
            ]
        ]
    ],
    "3": [
        [
            [
                1,
                37.42521772520066,
                70.20483824928897,
                28.216143300293048,
                -64.38354273409664,
                35.95761551674286,
                108.7411290795282,
                27.310052777030887,
                -47.54602012016767,
                20.652759820226365,
                20.265207958468864,
                24.569130931587907,
                -88.01513999192008,
                32.24984523986235
            ],
            [
                1,
                36.16120711794265,
                null,
                null,
                -64.61570974550813,
                35.97761551674286,
                104.47318069826076,
                28.310052777030883,
                -55.44636988779257,
                20.67733545438336,
                14.298798654479754,
                24.44913093158791,
                -89.91319214177184,
                32.84984523986236
            ]
        ]
    ],
    "4": [
        [
            [
                1,
                39.42521772520065,
                75.26937546174284,
                27.660364211452155,
                -63.24774162986775,
                35.83623164527301,
                114.39871155361313,
                26.34636366205066,
                -38.75579116768054,
                20.44182878215913,
                27.101251355275235,
                24.34983555888127,
                -84.8274537492509,
                31.389003498436143
            ],
            [
                1,
                37.42521772520066,
                70.20483824928897,
                28.216143300293048,
                -64.38354273409664,
                35.95761551674286,
                108.7411290795282,
                27.310052777030887,
                -47.54602012016767,
                20.652759820226365,
                20.265207958468864,
                24.569130931587907,
                -88.01513999192008,
                32.24984523986235
            ]
        ],
        [
            [
                2,
                32.90870700873732,
                18.06857828864304,
                22.886872352415338,
                null,
                null,
                null,
                null,
                null,
                null,
                85.91976469904904,
                33.31893352535796,
                -49.57133200406486,
                37.462607744555996
            ],
            [
                2,
                32.108707008737326,
                13.187660960482049,
                22.86687235241534,
                null,
                null,
                null,
                null,
                null,
                null,
                86.23287795735945,
                33.31893352535796,
                -47.1883816361555,
                37.422607744556004
            ]
        ]
    ],
    "5": [],
    "6": [],
    "7": [],
    "8": [],
    "9": [],
    "10": []
}