{
    "1": [
        [
            [
                2,
                21.740907967014394,
                18.512555127798976,
                25.757060834964705,
                -5.408787981187174,
                26.4662892495615,
                null,
                null,
                null,
                null,
                null,
                null,
                -108.32200694345767,
                22.479795623707922
            ],
            null
        ],
        [
            [
                2,
                21.658268631979716,
                104.6969006016846,
                37.394540911624034,
                -8.407088399552864,
                31.260303641228862,
                null,
                null,
                null,
                null,
                110.29141677999968,
                37.81537775726585,
                -55.170909374974144,
                37.80332140735057
            ],
            null
        ],
        [
            [
                2,
                23.436233677297807,
                null,
                null,
                -5.410411090590344,
                26.411131755326238,
                null,
                null,
                null,
                null,
                null,
                null,
                -42.713991729975476,
                37.51559827463488
            ],
            null
        ]
    ],
    "2": [],
    "3": [
        [
            [
                2,
                36.944035571466365,
                32.637254633050475,
                35.78564658672511,
                -39.76026438522695,
                33.331216582678465,
                null,
                null,
                null,
                null,
                17.194651445794534,
                22.71292294297933,
                -30.985030520174405,
                34.62907028781471
            ],
            [
                2,
                34.9899506320333,
                32.88546863462312,
                36.34564658672512,
                -40.93526538567761,
                33.41121658267846,
                null,
                null,
                null,
                null,
                10.974503625494265,
                23.712922942979326,
                null,
                null
            ]
        ]
    ],
    "4": [
        [
            [
                2,
                38.94403557146636,
                33.816449125421,
                34.92385181342941,
                -37.43385489083303,
                32.833202805395736,
                null,
                null,
                null,
                null,
                24.91020776003799,
                21.730104676119048,
                -29.465547878348445,
                35.90907028781471
            ],
            [
                2,
                36.944035571466365,
                32.637254633050475,
                35.78564658672511,
                -39.76026438522695,
                33.331216582678465,
                null,
                null,
                null,
                null,
                17.194651445794534,
                22.71292294297933,
                -30.985030520174405,
                34.62907028781471
            ]
        ]
    ],
    "5": [],
    "6": [],
    "7": [],
    "8": [],
    "9": [],
    "10": []
}