{
    "1": [
        [
            [
                2,
                32.39438470685875,
                8.626981518134322,
                20.141062057913892,
                -40.9023634754972,
                37.69740106643781,
                null,
                null,
                null,
                null,
                86.57145469571905,
                23.564352648946354,
                -76.74251828752689,
                38.64088422702645
            ],
            null
        ],
        [
            [
                2,
                33.35195635186846,
                9.144527337149983,
                20.263441651022276,
                -44.94970329968002,
                38.59535867770959,
                null,
                null,
                null,
                null,
                90.43469734817552,
                24.433303948069668,
                -76.63551949973072,
                39.376949782451284
            ],
            null
        ],
        [
            [
                2,
                33.30841601348163,
                9.339026260576926,
                20.320675698096125,
                -49.44626124921022,
                37.79051635146801,
                null,
                null,
                null,
                null,
                94.42431841012157,
                24.439359652145995,
                -72.94360296480897,
                39.32811249265166
            ],
            null
        ],
        [
            [
                2,
                31.219282993564086,
                7.818026764451817,
                21.34308664465155,
                -50.90134048101283,
                37.25808809598483,
                null,
                null,
                null,
                null,
                91.02551540088871,
                25.41420096263244,
                -69.60475314485062,
                39.38064128328709
            ],
            null
        ],
        [
            [
                1,
                24.01337962896211,
                22.234808097567026,
                36.452135825051755,
                -8.492562071178689,
                34.102799332375426,
                8.628568168191151,
                21.021455981433057,
                -5.433287728877714,
                34.30900842966218,
                23.35773214860309,
                27.209844028736104,
                -15.747365043949141,
                34.226406097036275
            ],
            null
        ]
    ],
    "2": [],
    "3": [
        [
            [
                1,
                34.128214866243866,
                21.902913679708902,
                35.34711762281296,
                -34.347111127002236,
                30.33488340149502,
                54.35565982358443,
                31.962415013402833,
                -6.017913270428238,
                33.7683357256822,
                94.13141260778346,
                26.265444507670512,
                -13.149497685377582,
                35.84122781799932
            ],
            [
                1,
                32.72746048827894,
                23.260847350071117,
                36.133939897821264,
                -5.72215665608212,
                33.70142742957933,
                53.861234918370315,
                32.220916594767054,
                -5.72215665608212,
                33.70142742957933,
                90.98447940587062,
                27.180377511303377,
                -11.899250113346682,
                35.468986641306365
            ]
        ]
    ],
    "4": [
        [
            [
                0,
                35.511429403070956,
                53.28849742079251,
                39.10311042230961,
                -46.76894363300289,
                34.59524379237773,
                14.734246009222602,
                28.12846772273965,
                -46.76894363300289,
                34.59524379237773,
                null,
                null,
                null,
                null
            ],
            [
                0,
                35.40245383248933,
                55.113805925950714,
                39.10311042230961,
                -47.19356844281066,
                34.59524379237773,
                11.37623316459576,
                29.128467722739646,
                null,
                null,
                null,
                null,
                null,
                null
            ]
        ]
    ],
    "5": [],
    "6": [],
    "7": [],
    "8": [],
    "9": [],
    "10": []
}