{
    "1": [
        [
            [
                1,
                31.392280040176686,
                7.358193228710434,
                24.80946999248179,
                -45.25896846947751,
                23.5310937250993,
                7.535380346343516,
                34.56832289021327,
                -104.9431408387897,
                29.491796891562657,
                35.1372899698261,
                39.540432171844216,
                -77.76067354826614,
                37.72308782740362
            ],
            null
        ]
    ],
    "2": [],
    "3": [],
    "4": [],
    "5": [],
    "6": [],
    "7": [],
    "8": [],
    "9": [],
    "10": []
}