{
    "1": [
        [
            [
                2,
                27.583974100836684,
                25.85601366733107,
                30.299469592245256,
                -5.687349392932333,
                29.475094295972767,
                null,
                null,
                null,
                null,
                60.51830231226916,
                35.2946682891534,
                null,
                null
            ],
            null
        ]
    ],
    "2": [],
    "3": [
        [
            [
                1,
                27.41185679733255,
                53.18157426036345,
                34.59274699539232,
                -7.618469588068579,
                30.775094295972764,
                23.74622798863127,
                29.251631302106667,
                -67.14540215832669,
                25.07265453844768,
                38.53143840182692,
                31.791373916299857,
                -37.40071269989393,
                34.144400763790436
            ],
            [
                1,
                27.583974100836684,
                56.75752956400885,
                34.817985129967376,
                -6.632909490500481,
                29.475094295972767,
                24.657791185637905,
                29.497482581879606,
                -6.632909490500481,
                29.475094295972767,
                40.892016739417556,
                32.642785718841715,
                -34.107278226032065,
                34.20482266710577
            ]
        ]
    ],
    "4": [],
    "5": [],
    "6": [],
    "7": [],
    "8": [],
    "9": [],
    "10": []
}